wfsx/CONST_j.py
wfsx/Excel_x.py
wfsx/Report.py
wfsx/__init__.py
wfsx/api.py
wfsx/apivalid.py
wfsx/apivalidation.py
wfsx/common.py
wfsx/dataextract.py
wfsx/excel_json_reader.py
wfsx/ghelper.py
wfsx/parseexcel.py
wfsx/plite.py
wfsx/results_validate.py
wfsx/retriveapi.py
wfsx/inix/endpointapi.ini
wfsx-1.13.1.dist-info/LICENSE
wfsx-1.13.1.dist-info/METADATA
wfsx-1.13.1.dist-info/WHEEL
wfsx-1.13.1.dist-info/top_level.txt
wfsx-1.13.1.dist-info/RECORD
