Metadata-Version: 2.1
Name: wfsx
Version: 1.13.1
Summary: api automation testing framework based on unittest.
Home-page: https://github.com/saasaa831/wfsx/
Author: saasaa
Author-email: saasaa@saa.com
License: Apache 2.0
Classifier: Intended Audience :: Developers
Classifier: Operating System :: MacOS :: MacOS X
Classifier: Operating System :: Microsoft :: Windows
Classifier: Programming Language :: Python
Classifier: Programming Language :: Python :: 3.7
Classifier: Programming Language :: Python :: 3.8
Classifier: Programming Language :: Python :: 3.9
Classifier: Programming Language :: Python :: 3.10
Classifier: Programming Language :: Python :: 3.11
Classifier: Topic :: Internet :: WWW/HTTP :: Dynamic Content
Classifier: Topic :: Software Development :: Testing
Requires-Python: >=3.10
License-File: LICENSE
Requires-Dist: openpyxl
Requires-Dist: urllib3
Requires-Dist: ijson
Requires-Dist: pandas
Requires-Dist: SQLAlchemy
Requires-Dist: configparser
Requires-Dist: numpy
Requires-Dist: selenium
Requires-Dist: cdxg (==1.3)
Requires-Dist: CXRunner (==1.0.6)
